saytex/__init__.py
saytex/compiler.py
saytex/config.py
saytex/divided_by_grammar.py
saytex/layers/__init__.py
saytex/layers/capitalization.py
saytex/layers/case_insensitivity.py
saytex/layers/divided_by_recognition.py
saytex/layers/from_to_recognition.py
saytex/layers/handle_of.py
saytex/layers/layer.py
saytex/layers/math_symbols_transform.py
saytex/layers/prettification.py
saytex/layers/speech_recognition_error_correction.py
saytex/layers/spoken_number_recognition.py
saytex/layers/synonym_standardization.py
saytex/layers/synonym_standardization_dictionary.json
saytex/saytexsyntax/__init__.py
saytex/saytexsyntax/compiler.py
saytex/saytexsyntax/config.py
saytex/saytexsyntax/syntax_dictionary.py
saytex/saytexsyntax/saytex_dictionary/controlflow.json
saytex/saytexsyntax/saytex_dictionary/functions.json
saytex/saytexsyntax/saytex_dictionary/greek.json
saytex/saytexsyntax/saytex_dictionary/misc.json
saytex/saytexsyntax/saytex_dictionary/operators.json
saytex/saytexsyntax/saytex_dictionary/symbols.json
saytex/saytexsyntax/saytex_dictionary/trigonometry.json
SayTeX-0.1.6.dist-info/LICENSE
SayTeX-0.1.6.dist-info/METADATA
SayTeX-0.1.6.dist-info/WHEEL
SayTeX-0.1.6.dist-info/top_level.txt
SayTeX-0.1.6.dist-info/RECORD
