Metadata-Version: 2.1
Name: SayTeX
Version: 0.1.6
Summary: Convert natural language math expressions into well-formatted LaTeX.
Home-page: https://saytex.xyz
Author: Arvid Lunnemark
Author-email: arvid.lunnemark@gmail.com
License: UNKNOWN
Project-URL: Documentation, https://saytex.readthedocs.io
Project-URL: Code, https://github.com/arvid220u/saytex
Platform: UNKNOWN
Classifier: Programming Language :: Python :: 3
Classifier: License :: OSI Approved :: MIT License
Classifier: Operating System :: OS Independent
